{
  "project_info": {
    "project_number": "177951679627",
    "project_id": "noteapp-b1ea3",
    "storage_bucket": "noteapp-b1ea3.firebasestorage.app"
  },
  "client": [
    {
      "client_info": {
        "mobilesdk_app_id": "1:177951679627:android:84ebc4bba72b1fa116e08e",
        "android_client_info": {
          "package_name": "com.project.notesapp"
        }
      },
      "oauth_client": [],
      "api_key": [
        {
          "current_key": "AIzaSyBZBgFOann551dxO1e-Ktn8iADSGNwGcSk"
        }
      ],
      "services": {
        "appinvite_service": {
          "other_platform_oauth_client": []
        }
      }
    }
  ],
  "configuration_version": "1"
}